Products.BastionLedger-5.0.3-py2.7-nspkg.pth
Products/BastionLedger/AccountPropertiesTool.py
Products/BastionLedger/BLAccount.py
Products/BastionLedger/BLAssetRegister.py
Products/BastionLedger/BLAssociations.py
Products/BastionLedger/BLAttachmentSupport.py
Products/BastionLedger/BLBase.py
Products/BastionLedger/BLControlEntry.py
Products/BastionLedger/BLEntry.py
Products/BastionLedger/BLEntryTemplate.py
Products/BastionLedger/BLForecaster.py
Products/BastionLedger/BLGlobals.py
Products/BastionLedger/BLInventory.py
Products/BastionLedger/BLLedger.py
Products/BastionLedger/BLObserverSupport.py
Products/BastionLedger/BLOpeningEntry.py
Products/BastionLedger/BLOrderBook.py
Products/BastionLedger/BLPayroll.py
Products/BastionLedger/BLPeriodInfo.py
Products/BastionLedger/BLProcess.py
Products/BastionLedger/BLQuoteManager.py
Products/BastionLedger/BLReport.py
Products/BastionLedger/BLShareholderLedger.py
Products/BastionLedger/BLSubsidiaryAccount.py
Products/BastionLedger/BLSubsidiaryEntry.py
Products/BastionLedger/BLSubsidiaryLedger.py
Products/BastionLedger/BLSubsidiaryTransaction.py
Products/BastionLedger/BLTaxCodeSupport.py
Products/BastionLedger/BLTaxTables.py
Products/BastionLedger/BLTransaction.py
Products/BastionLedger/BLTransactionTemplate.py
Products/BastionLedger/CMFAccount.py
Products/BastionLedger/DepreciationTool.py
Products/BastionLedger/Exceptions.py
Products/BastionLedger/FSBLProcess.py
Products/BastionLedger/LICENCE.txt
Products/BastionLedger/Ledger.py
Products/BastionLedger/LedgerControllerTool.py
Products/BastionLedger/LedgerTool.py
Products/BastionLedger/PeriodEndTool.py
Products/BastionLedger/Permissions.py
Products/BastionLedger/SyndicationSupport.py
Products/BastionLedger/__init__.py
Products/BastionLedger/catalog.py
Products/BastionLedger/config.py
Products/BastionLedger/configure.zcml
Products/BastionLedger/refresh.txt
Products/BastionLedger/setup.cfg
Products/BastionLedger/setuphandlers.py
Products/BastionLedger/tool.gif
Products.BastionLedger-5.0.3.dist-info/METADATA
Products.BastionLedger-5.0.3.dist-info/WHEEL
Products.BastionLedger-5.0.3.dist-info/entry_points.txt
Products.BastionLedger-5.0.3.dist-info/namespace_packages.txt
Products.BastionLedger-5.0.3.dist-info/test_info.txt
Products.BastionLedger-5.0.3.dist-info/top_level.txt
Products.BastionLedger-5.0.3.dist-info/RECORD
